<?xml version="1.0" encoding="UTF-8"?>
<dataset>
	<gtp_company_role>
		<company_id>2</company_id>
		<ROLENAME>cash_ft_meps_user</ROLENAME>
		<role_complete_name>Cash - Singapore Domestic Transfer - User</role_complete_name>
	</gtp_company_role>
	<gtp_company_role>
		<company_id>2</company_id>
		<ROLENAME>cash_meps_send</ROLENAME>
		<role_complete_name>Cash - Singapore Domestic Transfer - Sender</role_complete_name>
	</gtp_company_role>
	<gtp_company_role>
		<company_id>2</company_id>
		<ROLENAME>cash_meps_verify</ROLENAME>
		<role_complete_name>Cash - Singapore Domestic Transfer - Verifier</role_complete_name>
	</gtp_company_role>
	<gtp_company_role>
		<company_id>2</company_id>
		<ROLENAME>cash_ft_meps_user_entity</ROLENAME>
		<role_complete_name>Cash - Singapore Domestic Transfer - User - Entity</role_complete_name>
	</gtp_company_role>
	<gtp_company_role>
		<company_id>2</company_id>
		<ROLENAME>cash_meps_verifier_entity</ROLENAME>
		<role_complete_name>Cash - Singapore Domestic Transfer - Verifier -
			Entity</role_complete_name>
	</gtp_company_role>
	<gtp_company_role>
		<company_id>2</company_id>
		<ROLENAME>bank_cash_ft_meps_user</ROLENAME>
		<role_complete_name>Cash - Singapore Domestic Transfer - Bank</role_complete_name>
	</gtp_company_role>
	<gtp_company_role>
		<company_id>2</company_id>
		<ROLENAME>cash_meps_send_entity</ROLENAME>
		<role_complete_name>Cash - Singapore Domestic Transfer - Sender -
			Entity</role_complete_name>
	</gtp_company_role>
</dataset>