<?xml version="1.0" encoding="iso-8859-1"?>
<!-- 
	Copyright (c) 2000-2011 Misys (http://www.misys.com),
   	All Rights Reserved. 
-->
<menus id="menu_bank">
	<menu id="home_bank_default">
		<entry screen="CRM_SCREEN" title="MODULE_CRM_TITLE" description="MODULE_CRM_DESCRIPTION" permission="view_project"/>
		<entry screen="NEWS_SCREEN" title="MODULE_NEWSMAINTENANCE_TITLE" description="MODULE_NEWSMAINTENANCE_DESCRIPTION" permission="news_maintenance"/>
		<entry screen="BSF_SCREEN" title="MODULE_SYSTEMFEATURES_TITLE" description="MODULE_SYSTEMFEATURES_DESCRIPTION" permission="no_permission"/>
		<entry screen="AUDIT_SCREEN" title="MODULE_AUDIT_TITLE" description="MODULE_AUDIT_DESCRIPTION" permission="audit_access">
			<parameter name="option" value="AUDIT"/>
		</entry>
		<entry screen="TRADEADMIN_SCREEN" title="MODULE_TRADEADMIN_TITLE" description="MODULE_TRADEADMIN_DESCRIPTION" permission="tradeadmin_access"/>
		<entry screen="TMA_SCREEN" title="MODULE_TMA_TITLE" description="MODULE_TMA_DESCRIPTION" permission="tradeadmin_tm_access"/>
		<entry screen="MESSAGE_RESEND_SCREEN" title="MODULE_RESEND_FAIL" description="MODULE_RESEND_DESCRIPTION" permission="sy_messageresend_access"/>
		<!-- <entry screen="BSF_SCREEN" title="MODULE_ADMIN_MODULE_TITLE" description="MODULE_ADMIN_MODULE_DESCRIPTION" permission="no_permission"/> -->
		<entry screen="REPORTS_SCREEN" title="MODULE_REPORTS_TITLE" description="MODULE_REPORTS_DESCRIPTION" permission="tradeadmin_se_ktp_reports_access"/>
	</menu>
</menus>